README.md
setup.cfg
setup.py
tock/__init__.py
tock/__version__.py
tock/bot.py
tock/bus.py
tock/intent.py
tock/models.py
tock/schemas.py
tock/story.py
tock/webhook.py
tock/websocket.py
tock/session/__init__.py
tock/session/file.py
tock/session/memory.py
tock/session/session.py
tock/session/storage.py
tock/tests/__init__.py
tock/tests/test_schemas.py
tock/tests/session/__init__.py
tock/tests/session/test_file.py
tock/tests/session/test_memory.py
tock_py.egg-info/PKG-INFO
tock_py.egg-info/SOURCES.txt
tock_py.egg-info/dependency_links.txt
tock_py.egg-info/requires.txt
tock_py.egg-info/top_level.txt