Metadata-Version: 2.1
Name: tock-py
Version: 0.0.1.dev10
Summary: Build chatbots using Tock and Python
Home-page: https://github.com/theopenconversationkit/tock-py/
Author: Erwan LE BESCOND
Author-email: elebescond@gmail.com
License: UNKNOWN
Platform: UNKNOWN
Classifier: Programming Language :: Python :: 3
Classifier: License :: OSI Approved :: MIT License
Classifier: Operating System :: OS Independent
Requires-Python: >=3.6
